{
  "version": 2,
  "normal": {
    "1": {
      "assetWidth": 240,
      "assetHeight": 240,
      "opticalCenterX": 116.0,
      "opticalCenterY": 97.0,
      "innerApertureRatio": 0.6749,
      "outerVisibleRatio": 0.8625,
      "frameScale": 1.3101,
      "avatarScale": 0.7086,
      "frameOffsetXPercent": -0.62,
      "frameOffsetYPercent": 3.12,
      "avatarOffsetXPercent": -1.46,
      "avatarOffsetYPercent": -9.38,
      "thicknessProfile": "thick"
    },
    "2": {
      "assetWidth": 240,
      "assetHeight": 240,
      "opticalCenterX": 120.0,
      "opticalCenterY": 98.0,
      "innerApertureRatio": 0.7491,
      "outerVisibleRatio": 0.8875,
      "frameScale": 1.2732,
      "avatarScale": 0.7866,
      "frameOffsetXPercent": -0.21,
      "frameOffsetYPercent": -1.67,
      "avatarOffsetXPercent": 0.21,
      "avatarOffsetYPercent": -8.96,
      "thicknessProfile": "thick"
    },
    "3": {
      "assetWidth": 240,
      "assetHeight": 240,
      "opticalCenterX": 123.0,
      "opticalCenterY": 127.0,
      "innerApertureRatio": 0.5201,
      "outerVisibleRatio": 0.9792,
      "frameScale": 1.154,
      "avatarScale": 0.64,
      "frameOffsetXPercent": 2.08,
      "frameOffsetYPercent": -1.04,
      "avatarOffsetXPercent": 1.46,
      "avatarOffsetYPercent": 3.12,
      "thicknessProfile": "ultra"
    },
    "4": {
      "assetWidth": 240,
      "assetHeight": 240,
      "opticalCenterX": 120.0,
      "opticalCenterY": 120.0,
      "innerApertureRatio": 0.4363,
      "outerVisibleRatio": 0.975,
      "frameScale": 1.159,
      "avatarScale": 0.64,
      "frameOffsetXPercent": 1.04,
      "frameOffsetYPercent": 1.25,
      "avatarOffsetXPercent": 0.21,
      "avatarOffsetYPercent": 0.21,
      "thicknessProfile": "ultra"
    },
    "5": {
      "assetWidth": 160,
      "assetHeight": 160,
      "opticalCenterX": 79.0,
      "opticalCenterY": 71.0,
      "innerApertureRatio": 0.7711,
      "outerVisibleRatio": 0.9875,
      "frameScale": 1.1443,
      "avatarScale": 0.8096,
      "frameOffsetXPercent": 0.0,
      "frameOffsetYPercent": 0.62,
      "avatarOffsetXPercent": -0.31,
      "avatarOffsetYPercent": -5.31,
      "thicknessProfile": "normal"
    },
    "6": {
      "assetWidth": 240,
      "assetHeight": 240,
      "opticalCenterX": 117.0,
      "opticalCenterY": 117.0,
      "innerApertureRatio": 0.6177,
      "outerVisibleRatio": 0.9542,
      "frameScale": 1.1843,
      "avatarScale": 0.6485,
      "frameOffsetXPercent": 1.04,
      "frameOffsetYPercent": -0.62,
      "avatarOffsetXPercent": -1.04,
      "avatarOffsetYPercent": -1.04,
      "thicknessProfile": "ultra"
    },
    "7": {
      "assetWidth": 240,
      "assetHeight": 240,
      "opticalCenterX": 120.0,
      "opticalCenterY": 93.0,
      "innerApertureRatio": 0.7001,
      "outerVisibleRatio": 0.9583,
      "frameScale": 1.1791,
      "avatarScale": 0.7351,
      "frameOffsetXPercent": -0.62,
      "frameOffsetYPercent": 1.67,
      "avatarOffsetXPercent": 0.21,
      "avatarOffsetYPercent": -11.04,
      "thicknessProfile": "thick"
    },
    "8": {
      "assetWidth": 240,
      "assetHeight": 240,
      "opticalCenterX": 118.0,
      "opticalCenterY": 106.0,
      "innerApertureRatio": 0.4621,
      "outerVisibleRatio": 0.95,
      "frameScale": 1.1895,
      "avatarScale": 0.64,
      "frameOffsetXPercent": 0.42,
      "frameOffsetYPercent": 0.42,
      "avatarOffsetXPercent": -0.62,
      "avatarOffsetYPercent": -5.62,
      "thicknessProfile": "ultra"
    },
    "9": {
      "assetWidth": 240,
      "assetHeight": 240,
      "opticalCenterX": 130.0,
      "opticalCenterY": 123.0,
      "innerApertureRatio": 0.4568,
      "outerVisibleRatio": 0.9917,
      "frameScale": 1.1395,
      "avatarScale": 0.64,
      "frameOffsetXPercent": -0.42,
      "frameOffsetYPercent": -0.62,
      "avatarOffsetXPercent": 4.38,
      "avatarOffsetYPercent": 1.46,
      "thicknessProfile": "ultra"
    },
    "10": {
      "assetWidth": 240,
      "assetHeight": 240,
      "opticalCenterX": 121.0,
      "opticalCenterY": 118.0,
      "innerApertureRatio": 0.679,
      "outerVisibleRatio": 0.9708,
      "frameScale": 1.1639,
      "avatarScale": 0.7129,
      "frameOffsetXPercent": 0.42,
      "frameOffsetYPercent": -1.46,
      "avatarOffsetXPercent": 0.62,
      "avatarOffsetYPercent": -0.62,
      "thicknessProfile": "thick"
    },
    "11": {
      "assetWidth": 240,
      "assetHeight": 240,
      "opticalCenterX": 116.0,
      "opticalCenterY": 114.0,
      "innerApertureRatio": 0.5968,
      "outerVisibleRatio": 0.8333,
      "frameScale": 1.356,
      "avatarScale": 0.64,
      "frameOffsetXPercent": 0.42,
      "frameOffsetYPercent": 0.21,
      "avatarOffsetXPercent": -1.46,
      "avatarOffsetYPercent": -2.29,
      "thicknessProfile": "ultra"
    },
    "12": {
      "assetWidth": 240,
      "assetHeight": 240,
      "opticalCenterX": 118.0,
      "opticalCenterY": 125.0,
      "innerApertureRatio": 0.6462,
      "outerVisibleRatio": 0.8917,
      "frameScale": 1.2673,
      "avatarScale": 0.6785,
      "frameOffsetXPercent": -0.21,
      "frameOffsetYPercent": 0.42,
      "avatarOffsetXPercent": -0.62,
      "avatarOffsetYPercent": 2.29,
      "thicknessProfile": "thick"
    },
    "13": {
      "assetWidth": 240,
      "assetHeight": 240,
      "opticalCenterX": 120.0,
      "opticalCenterY": 122.0,
      "innerApertureRatio": 0.751,
      "outerVisibleRatio": 0.9042,
      "frameScale": 1.2498,
      "avatarScale": 0.7886,
      "frameOffsetXPercent": 0.21,
      "frameOffsetYPercent": -1.04,
      "avatarOffsetXPercent": 0.21,
      "avatarOffsetYPercent": 1.04,
      "thicknessProfile": "thick"
    },
    "14": {
      "assetWidth": 240,
      "assetHeight": 240,
      "opticalCenterX": 116.0,
      "opticalCenterY": 129.0,
      "innerApertureRatio": 0.4583,
      "outerVisibleRatio": 0.8958,
      "frameScale": 1.2614,
      "avatarScale": 0.64,
      "frameOffsetXPercent": -5.62,
      "frameOffsetYPercent": -5.21,
      "avatarOffsetXPercent": -1.46,
      "avatarOffsetYPercent": 3.96,
      "thicknessProfile": "ultra"
    },
    "15": {
      "assetWidth": 240,
      "assetHeight": 240,
      "opticalCenterX": 119.0,
      "opticalCenterY": 117.0,
      "innerApertureRatio": 0.6015,
      "outerVisibleRatio": 0.9333,
      "frameScale": 1.2107,
      "avatarScale": 0.64,
      "frameOffsetXPercent": -0.42,
      "frameOffsetYPercent": -0.83,
      "avatarOffsetXPercent": -0.21,
      "avatarOffsetYPercent": -1.04,
      "thicknessProfile": "ultra"
    },
    "16": {
      "assetWidth": 240,
      "assetHeight": 240,
      "opticalCenterX": 120.0,
      "opticalCenterY": 141.0,
      "innerApertureRatio": 0.484,
      "outerVisibleRatio": 0.925,
      "frameScale": 1.2216,
      "avatarScale": 0.64,
      "frameOffsetXPercent": 0.0,
      "frameOffsetYPercent": -2.5,
      "avatarOffsetXPercent": 0.21,
      "avatarOffsetYPercent": 8.96,
      "thicknessProfile": "ultra"
    },
    "17": {
      "assetWidth": 240,
      "assetHeight": 240,
      "opticalCenterX": 121.0,
      "opticalCenterY": 111.0,
      "innerApertureRatio": 0.4729,
      "outerVisibleRatio": 0.9333,
      "frameScale": 1.2107,
      "avatarScale": 0.64,
      "frameOffsetXPercent": 0.0,
      "frameOffsetYPercent": -0.21,
      "avatarOffsetXPercent": 0.62,
      "avatarOffsetYPercent": -3.54,
      "thicknessProfile": "ultra"
    },
    "18": {
      "assetWidth": 240,
      "assetHeight": 240,
      "opticalCenterX": 110.0,
      "opticalCenterY": 113.0,
      "innerApertureRatio": 0.3911,
      "outerVisibleRatio": 0.7708,
      "frameScale": 1.4659,
      "avatarScale": 0.64,
      "frameOffsetXPercent": -0.21,
      "frameOffsetYPercent": -0.83,
      "avatarOffsetXPercent": -3.96,
      "avatarOffsetYPercent": -2.71,
      "thicknessProfile": "ultra"
    }
  },
  "market": {
    "1": {
      "assetWidth": 224,
      "assetHeight": 224,
      "opticalCenterX": 112.0,
      "opticalCenterY": 117.0,
      "innerApertureRatio": 0.7509,
      "outerVisibleRatio": 0.9955,
      "frameScale": 1.1351,
      "avatarScale": 0.7885,
      "frameOffsetXPercent": -1.12,
      "frameOffsetYPercent": 0.22,
      "avatarOffsetXPercent": 0.22,
      "avatarOffsetYPercent": 2.46,
      "thicknessProfile": "thick"
    },
    "2": {
      "assetWidth": 230,
      "assetHeight": 240,
      "opticalCenterX": 111.0,
      "opticalCenterY": 121.0,
      "innerApertureRatio": 0.8739,
      "outerVisibleRatio": 0.9625,
      "frameScale": 1.174,
      "avatarScale": 0.9176,
      "frameOffsetXPercent": 0.0,
      "frameOffsetYPercent": 1.88,
      "avatarOffsetXPercent": -1.46,
      "avatarOffsetYPercent": 0.62,
      "thicknessProfile": "normal"
    },
    "3": {
      "assetWidth": 240,
      "assetHeight": 240,
      "opticalCenterX": 115.0,
      "opticalCenterY": 101.0,
      "innerApertureRatio": 0.5155,
      "outerVisibleRatio": 0.9792,
      "frameScale": 1.154,
      "avatarScale": 0.64,
      "frameOffsetXPercent": 0.62,
      "frameOffsetYPercent": 0.21,
      "avatarOffsetXPercent": -1.88,
      "avatarOffsetYPercent": -7.71,
      "thicknessProfile": "ultra"
    },
    "4": {
      "assetWidth": 240,
      "assetHeight": 240,
      "opticalCenterX": 127.0,
      "opticalCenterY": 108.0,
      "innerApertureRatio": 0.589,
      "outerVisibleRatio": 0.9583,
      "frameScale": 1.1791,
      "avatarScale": 0.64,
      "frameOffsetXPercent": -1.88,
      "frameOffsetYPercent": -0.42,
      "avatarOffsetXPercent": 3.12,
      "avatarOffsetYPercent": -4.79,
      "thicknessProfile": "ultra"
    },
    "5": {
      "assetWidth": 240,
      "assetHeight": 238,
      "opticalCenterX": 115.0,
      "opticalCenterY": 113.0,
      "innerApertureRatio": 0.7804,
      "outerVisibleRatio": 0.8208,
      "frameScale": 1.3766,
      "avatarScale": 0.8195,
      "frameOffsetXPercent": 0.21,
      "frameOffsetYPercent": -0.83,
      "avatarOffsetXPercent": -1.88,
      "avatarOffsetYPercent": -2.29,
      "thicknessProfile": "normal"
    },
    "6": {
      "assetWidth": 240,
      "assetHeight": 240,
      "opticalCenterX": 108.0,
      "opticalCenterY": 112.0,
      "innerApertureRatio": 0.7423,
      "outerVisibleRatio": 0.9542,
      "frameScale": 1.1843,
      "avatarScale": 0.7794,
      "frameOffsetXPercent": 1.25,
      "frameOffsetYPercent": 0.21,
      "avatarOffsetXPercent": -4.79,
      "avatarOffsetYPercent": -3.12,
      "thicknessProfile": "thick"
    },
    "7": {
      "assetWidth": 240,
      "assetHeight": 240,
      "opticalCenterX": 119.0,
      "opticalCenterY": 112.0,
      "innerApertureRatio": 0.5925,
      "outerVisibleRatio": 0.9667,
      "frameScale": 1.169,
      "avatarScale": 0.64,
      "frameOffsetXPercent": -1.25,
      "frameOffsetYPercent": 0.83,
      "avatarOffsetXPercent": -0.21,
      "avatarOffsetYPercent": -3.12,
      "thicknessProfile": "ultra"
    },
    "8": {
      "assetWidth": 224,
      "assetHeight": 224,
      "opticalCenterX": 111.0,
      "opticalCenterY": 111.0,
      "innerApertureRatio": 0.7894,
      "outerVisibleRatio": 0.933,
      "frameScale": 1.2111,
      "avatarScale": 0.8288,
      "frameOffsetXPercent": 3.35,
      "frameOffsetYPercent": 0.0,
      "avatarOffsetXPercent": -0.22,
      "avatarOffsetYPercent": -0.22,
      "thicknessProfile": "normal"
    },
    "9": {
      "assetWidth": 224,
      "assetHeight": 224,
      "opticalCenterX": 118.0,
      "opticalCenterY": 106.0,
      "innerApertureRatio": 0.5593,
      "outerVisibleRatio": 0.9375,
      "frameScale": 1.2053,
      "avatarScale": 0.64,
      "frameOffsetXPercent": 1.12,
      "frameOffsetYPercent": -0.45,
      "avatarOffsetXPercent": 2.9,
      "avatarOffsetYPercent": -2.46,
      "thicknessProfile": "ultra"
    },
    "10": {
      "assetWidth": 224,
      "assetHeight": 224,
      "opticalCenterX": 110.0,
      "opticalCenterY": 109.0,
      "innerApertureRatio": 0.7278,
      "outerVisibleRatio": 0.9509,
      "frameScale": 1.1884,
      "avatarScale": 0.7642,
      "frameOffsetXPercent": 0.67,
      "frameOffsetYPercent": 0.45,
      "avatarOffsetXPercent": -0.67,
      "avatarOffsetYPercent": -1.12,
      "thicknessProfile": "thick"
    },
    "11": {
      "assetWidth": 240,
      "assetHeight": 240,
      "opticalCenterX": 105.0,
      "opticalCenterY": 113.0,
      "innerApertureRatio": 0.5848,
      "outerVisibleRatio": 0.9917,
      "frameScale": 1.1395,
      "avatarScale": 0.64,
      "frameOffsetXPercent": -0.21,
      "frameOffsetYPercent": 0.42,
      "avatarOffsetXPercent": -6.04,
      "avatarOffsetYPercent": -2.71,
      "thicknessProfile": "ultra"
    },
    "12": {
      "assetWidth": 240,
      "assetHeight": 240,
      "opticalCenterX": 137.0,
      "opticalCenterY": 107.0,
      "innerApertureRatio": 0.7011,
      "outerVisibleRatio": 0.9417,
      "frameScale": 1.2,
      "avatarScale": 0.7362,
      "frameOffsetXPercent": -0.21,
      "frameOffsetYPercent": 0.42,
      "avatarOffsetXPercent": 7.29,
      "avatarOffsetYPercent": -5.21,
      "thicknessProfile": "thick"
    },
    "13": {
      "assetWidth": 240,
      "assetHeight": 240,
      "opticalCenterX": 109.0,
      "opticalCenterY": 132.0,
      "innerApertureRatio": 0.6242,
      "outerVisibleRatio": 0.975,
      "frameScale": 1.159,
      "avatarScale": 0.6554,
      "frameOffsetXPercent": 0.83,
      "frameOffsetYPercent": -1.25,
      "avatarOffsetXPercent": -4.38,
      "avatarOffsetYPercent": 5.21,
      "thicknessProfile": "thick"
    },
    "14": {
      "assetWidth": 160,
      "assetHeight": 160,
      "opticalCenterX": 72.0,
      "opticalCenterY": 82.0,
      "innerApertureRatio": 0.6544,
      "outerVisibleRatio": 0.95,
      "frameScale": 1.1895,
      "avatarScale": 0.6871,
      "frameOffsetXPercent": 3.12,
      "frameOffsetYPercent": -0.62,
      "avatarOffsetXPercent": -4.69,
      "avatarOffsetYPercent": 1.56,
      "thicknessProfile": "thick"
    },
    "15": {
      "assetWidth": 239,
      "assetHeight": 239,
      "opticalCenterX": 125.0,
      "opticalCenterY": 124.0,
      "innerApertureRatio": 0.6609,
      "outerVisibleRatio": 0.8494,
      "frameScale": 1.3304,
      "avatarScale": 0.6939,
      "frameOffsetXPercent": 0.0,
      "frameOffsetYPercent": 0.0,
      "avatarOffsetXPercent": 2.51,
      "avatarOffsetYPercent": 2.09,
      "thicknessProfile": "thick"
    },
    "16": {
      "assetWidth": 240,
      "assetHeight": 240,
      "opticalCenterX": 117.0,
      "opticalCenterY": 122.0,
      "innerApertureRatio": 0.6257,
      "outerVisibleRatio": 0.8583,
      "frameScale": 1.3165,
      "avatarScale": 0.657,
      "frameOffsetXPercent": -0.42,
      "frameOffsetYPercent": -0.83,
      "avatarOffsetXPercent": -1.04,
      "avatarOffsetYPercent": 1.04,
      "thicknessProfile": "thick"
    },
    "17": {
      "assetWidth": 180,
      "assetHeight": 240,
      "opticalCenterX": 75.0,
      "opticalCenterY": 109.0,
      "innerApertureRatio": 0.5309,
      "outerVisibleRatio": 0.7792,
      "frameScale": 1.4503,
      "avatarScale": 0.64,
      "frameOffsetXPercent": 0.0,
      "frameOffsetYPercent": 0.62,
      "avatarOffsetXPercent": -6.04,
      "avatarOffsetYPercent": -4.38,
      "thicknessProfile": "ultra"
    },
    "18": {
      "assetWidth": 224,
      "assetHeight": 239,
      "opticalCenterX": 114.0,
      "opticalCenterY": 119.0,
      "innerApertureRatio": 0.6084,
      "outerVisibleRatio": 0.887,
      "frameScale": 1.2739,
      "avatarScale": 0.64,
      "frameOffsetXPercent": -0.21,
      "frameOffsetYPercent": -2.72,
      "avatarOffsetXPercent": 1.05,
      "avatarOffsetYPercent": 0.0,
      "thicknessProfile": "ultra"
    },
    "19": {
      "assetWidth": 240,
      "assetHeight": 187,
      "opticalCenterX": 119.0,
      "opticalCenterY": 89.0,
      "innerApertureRatio": 0.4645,
      "outerVisibleRatio": 0.7083,
      "frameScale": 1.52,
      "avatarScale": 0.64,
      "frameOffsetXPercent": -0.42,
      "frameOffsetYPercent": 0.83,
      "avatarOffsetXPercent": -0.21,
      "avatarOffsetYPercent": -1.67,
      "thicknessProfile": "ultra"
    },
    "20": {
      "assetWidth": 227,
      "assetHeight": 240,
      "opticalCenterX": 113.0,
      "opticalCenterY": 119.0,
      "innerApertureRatio": 0.5566,
      "outerVisibleRatio": 0.9292,
      "frameScale": 1.2161,
      "avatarScale": 0.64,
      "frameOffsetXPercent": -0.42,
      "frameOffsetYPercent": -1.88,
      "avatarOffsetXPercent": 0.0,
      "avatarOffsetYPercent": -0.21,
      "thicknessProfile": "ultra"
    },
    "21": {
      "assetWidth": 240,
      "assetHeight": 240,
      "opticalCenterX": 121.0,
      "opticalCenterY": 111.0,
      "innerApertureRatio": 0.4729,
      "outerVisibleRatio": 0.9333,
      "frameScale": 1.2107,
      "avatarScale": 0.64,
      "frameOffsetXPercent": 0.0,
      "frameOffsetYPercent": -0.21,
      "avatarOffsetXPercent": 0.62,
      "avatarOffsetYPercent": -3.54,
      "thicknessProfile": "ultra"
    },
    "22": {
      "assetWidth": 240,
      "assetHeight": 240,
      "opticalCenterX": 122.0,
      "opticalCenterY": 108.0,
      "innerApertureRatio": 0.4559,
      "outerVisibleRatio": 0.9917,
      "frameScale": 1.1395,
      "avatarScale": 0.64,
      "frameOffsetXPercent": 0.0,
      "frameOffsetYPercent": -0.62,
      "avatarOffsetXPercent": 1.04,
      "avatarOffsetYPercent": -4.79,
      "thicknessProfile": "ultra"
    },
    "23": {
      "assetWidth": 240,
      "assetHeight": 240,
      "opticalCenterX": 120.0,
      "opticalCenterY": 114.0,
      "innerApertureRatio": 0.4896,
      "outerVisibleRatio": 0.925,
      "frameScale": 1.2216,
      "avatarScale": 0.64,
      "frameOffsetXPercent": 0.42,
      "frameOffsetYPercent": 1.46,
      "avatarOffsetXPercent": 0.21,
      "avatarOffsetYPercent": -2.29,
      "thicknessProfile": "ultra"
    },
    "24": {
      "assetWidth": 240,
      "assetHeight": 240,
      "opticalCenterX": 116.0,
      "opticalCenterY": 122.0,
      "innerApertureRatio": 0.5224,
      "outerVisibleRatio": 0.9375,
      "frameScale": 1.2053,
      "avatarScale": 0.64,
      "frameOffsetXPercent": 0.21,
      "frameOffsetYPercent": 0.0,
      "avatarOffsetXPercent": -1.46,
      "avatarOffsetYPercent": 1.04,
      "thicknessProfile": "ultra"
    },
    "25": {
      "assetWidth": 240,
      "assetHeight": 240,
      "opticalCenterX": 114.0,
      "opticalCenterY": 116.0,
      "innerApertureRatio": 0.4345,
      "outerVisibleRatio": 0.9167,
      "frameScale": 1.2327,
      "avatarScale": 0.64,
      "frameOffsetXPercent": 0.0,
      "frameOffsetYPercent": -1.67,
      "avatarOffsetXPercent": -2.29,
      "avatarOffsetYPercent": -1.46,
      "thicknessProfile": "ultra"
    },
    "26": {
      "assetWidth": 240,
      "assetHeight": 240,
      "opticalCenterX": 114.0,
      "opticalCenterY": 114.0,
      "innerApertureRatio": 0.3876,
      "outerVisibleRatio": 0.9042,
      "frameScale": 1.2498,
      "avatarScale": 0.64,
      "frameOffsetXPercent": 0.21,
      "frameOffsetYPercent": -0.42,
      "avatarOffsetXPercent": -2.29,
      "avatarOffsetYPercent": -2.29,
      "thicknessProfile": "ultra"
    },
    "27": {
      "assetWidth": 240,
      "assetHeight": 240,
      "opticalCenterX": 120.0,
      "opticalCenterY": 117.0,
      "innerApertureRatio": 0.4632,
      "outerVisibleRatio": 0.9417,
      "frameScale": 1.2,
      "avatarScale": 0.64,
      "frameOffsetXPercent": 0.0,
      "frameOffsetYPercent": 2.5,
      "avatarOffsetXPercent": 0.21,
      "avatarOffsetYPercent": -1.04,
      "thicknessProfile": "ultra"
    },
    "28": {
      "assetWidth": 240,
      "assetHeight": 240,
      "opticalCenterX": 119.0,
      "opticalCenterY": 118.0,
      "innerApertureRatio": 0.3672,
      "outerVisibleRatio": 0.9458,
      "frameScale": 1.1947,
      "avatarScale": 0.64,
      "frameOffsetXPercent": 0.21,
      "frameOffsetYPercent": 0.62,
      "avatarOffsetXPercent": -0.21,
      "avatarOffsetYPercent": -0.62,
      "thicknessProfile": "ultra"
    },
    "29": {
      "assetWidth": 240,
      "assetHeight": 240,
      "opticalCenterX": 121.0,
      "opticalCenterY": 115.0,
      "innerApertureRatio": 0.5706,
      "outerVisibleRatio": 0.9083,
      "frameScale": 1.244,
      "avatarScale": 0.64,
      "frameOffsetXPercent": 0.0,
      "frameOffsetYPercent": 0.42,
      "avatarOffsetXPercent": 0.62,
      "avatarOffsetYPercent": -1.88,
      "thicknessProfile": "ultra"
    },
    "30": {
      "assetWidth": 240,
      "assetHeight": 240,
      "opticalCenterX": 122.0,
      "opticalCenterY": 90.0,
      "innerApertureRatio": 0.4759,
      "outerVisibleRatio": 0.95,
      "frameScale": 1.1895,
      "avatarScale": 0.64,
      "frameOffsetXPercent": 0.42,
      "frameOffsetYPercent": 0.62,
      "avatarOffsetXPercent": 1.04,
      "avatarOffsetYPercent": -12.29,
      "thicknessProfile": "ultra"
    },
    "31": {
      "assetWidth": 212,
      "assetHeight": 240,
      "opticalCenterX": 97.0,
      "opticalCenterY": 119.0,
      "innerApertureRatio": 0.401,
      "outerVisibleRatio": 1.0,
      "frameScale": 1.13,
      "avatarScale": 0.64,
      "frameOffsetXPercent": 0.21,
      "frameOffsetYPercent": 0.0,
      "avatarOffsetXPercent": -3.54,
      "avatarOffsetYPercent": -0.21,
      "thicknessProfile": "ultra"
    },
    "32": {
      "assetWidth": 240,
      "assetHeight": 213,
      "opticalCenterX": 119.0,
      "opticalCenterY": 106.0,
      "innerApertureRatio": 0.4709,
      "outerVisibleRatio": 1.0,
      "frameScale": 1.13,
      "avatarScale": 0.64,
      "frameOffsetXPercent": 0.0,
      "frameOffsetYPercent": -0.21,
      "avatarOffsetXPercent": -0.21,
      "avatarOffsetYPercent": 0.0,
      "thicknessProfile": "ultra"
    }
  }
}
